<?xml version="1.0" encoding="utf-8" ?>
<dwsync>
<file name="ajax.html" server="192.185.136.173//public_html/" local="130945128180000000" remote="130964860200000000" Dst="1" />
<file name="api.html" server="192.185.136.173//public_html/" local="130945128180000000" remote="130964860200000000" Dst="1" />
<file name="appendto.html" server="192.185.136.173//public_html/" local="130945128180000000" remote="130964860200000000" Dst="1" />
<file name="datafiltering.html" server="192.185.136.173//public_html/" local="130945128180000000" remote="130964860200000000" Dst="1" />
<file name="divreplace.html" server="192.185.136.173//public_html/" local="130945128180000000" remote="130964860200000000" Dst="1" />
<file name="index.html" server="192.185.136.173//public_html/" local="130945128180000000" remote="130964860200000000" Dst="1" />
<file name="inlineall.html" server="192.185.136.173//public_html/" local="130945128180000000" remote="130964860200000000" Dst="1" />
<file name="inlinebycode.html" server="192.185.136.173//public_html/" local="130945128180000000" remote="130964860200000000" Dst="1" />
<file name="inlinetextarea.html" server="192.185.136.173//public_html/" local="130945128180000000" remote="130964860200000000" Dst="1" />
<file name="jquery.html" server="192.185.136.173//public_html/" local="130945128180000000" remote="130964860200000000" Dst="1" />
<file name="readonly.html" server="192.185.136.173//public_html/" local="130945128180000000" remote="130964860200000000" Dst="1" />
<file name="replacebyclass.html" server="192.185.136.173//public_html/" local="130945128180000000" remote="130964860200000000" Dst="1" />
<file name="replacebycode.html" server="192.185.136.173//public_html/" local="130945128180000000" remote="130964860200000000" Dst="1" />
<file name="sample_posteddata.php" server="192.185.136.173//public_html/" local="130945128180000000" remote="130964860200000000" Dst="1" />
<file name="sample.css" server="192.185.136.173//public_html/" local="130945128180000000" remote="130964860200000000" Dst="1" />
<file name="sample.js" server="192.185.136.173//public_html/" local="130945128180000000" remote="130964860200000000" Dst="1" />
<file name="tabindex.html" server="192.185.136.173//public_html/" local="130945128180000000" remote="130964860200000000" Dst="1" />
<file name="uicolor.html" server="192.185.136.173//public_html/" local="130945128180000000" remote="130964860200000000" Dst="1" />
<file name="uilanguages.html" server="192.185.136.173//public_html/" local="130945128180000000" remote="130964860200000000" Dst="1" />
<file name="xhtmlstyle.html" server="192.185.136.173//public_html/" local="130945128180000000" remote="130964860200000000" Dst="1" />
<file name="ajax.html" server="192.185.136.173/public_html/" local="130977732823200082" remote="130964860200000000" Dst="1" />
<file name="api.html" server="192.185.136.173/public_html/" local="130977732823603478" remote="130964860200000000" Dst="1" />
<file name="appendto.html" server="192.185.136.173/public_html/" local="130977732824667631" remote="130964860200000000" Dst="1" />
<file name="datafiltering.html" server="192.185.136.173/public_html/" local="130977732829057846" remote="130964860200000000" Dst="1" />
<file name="divreplace.html" server="192.185.136.173/public_html/" local="130977732829877638" remote="130964860200000000" Dst="1" />
<file name="index.html" server="192.185.136.173/public_html/" local="130977732834238128" remote="130964860200000000" Dst="1" />
<file name="inlineall.html" server="192.185.136.173/public_html/" local="130977732835648233" remote="130964860200000000" Dst="1" />
<file name="inlinebycode.html" server="192.185.136.173/public_html/" local="130977732835733247" remote="130964860200000000" Dst="1" />
<file name="inlinetextarea.html" server="192.185.136.173/public_html/" local="130977732835833255" remote="130964860200000000" Dst="1" />
<file name="readonly.html" server="192.185.136.173/public_html/" local="130977732837173742" remote="130964860200000000" Dst="1" />
<file name="jquery.html" server="192.185.136.173/public_html/" local="130977732837308534" remote="130964860200000000" Dst="1" />
<file name="replacebyclass.html" server="192.185.136.173/public_html/" local="130977732838837751" remote="130964860200000000" Dst="1" />
<file name="replacebycode.html" server="192.185.136.173/public_html/" local="130977732838912761" remote="130964860200000000" Dst="1" />
<file name="sample.css" server="192.185.136.173/public_html/" local="130977732839078045" remote="130964860200000000" Dst="1" />
<file name="sample.js" server="192.185.136.173/public_html/" local="130977732840291356" remote="130964860200000000" Dst="1" />
<file name="sample_posteddata.php" server="192.185.136.173/public_html/" local="130977732840545938" remote="130964860200000000" Dst="1" />
<file name="tabindex.html" server="192.185.136.173/public_html/" local="130977732840805960" remote="130964860200000000" Dst="1" />
<file name="uicolor.html" server="192.185.136.173/public_html/" local="130977732842221836" remote="130964860200000000" Dst="1" />
<file name="uilanguages.html" server="192.185.136.173/public_html/" local="130977732842728914" remote="130964860200000000" Dst="1" />
<file name="xhtmlstyle.html" server="192.185.136.173/public_html/" local="130977732843888123" remote="130964860200000000" Dst="1" />
<file name="ajax.html" server="gpo.firespike.com/gpo.firespike.com/" local="130941733640000000" remote="130977792370000000" Dst="1" />
<file name="api.html" server="gpo.firespike.com/gpo.firespike.com/" local="130941733640000000" remote="130977792380000000" Dst="1" />
<file name="appendto.html" server="gpo.firespike.com/gpo.firespike.com/" local="130941733640000000" remote="130977792380000000" Dst="1" />
<file name="datafiltering.html" server="gpo.firespike.com/gpo.firespike.com/" local="130941733640000000" remote="130977792430000000" Dst="1" />
<file name="divreplace.html" server="gpo.firespike.com/gpo.firespike.com/" local="130941733640000000" remote="130977792460000000" Dst="1" />
<file name="index.html" server="gpo.firespike.com/gpo.firespike.com/" local="130941733640000000" remote="130977792510000000" Dst="1" />
<file name="inlineall.html" server="gpo.firespike.com/gpo.firespike.com/" local="130941733640000000" remote="130977792520000000" Dst="1" />
<file name="inlinebycode.html" server="gpo.firespike.com/gpo.firespike.com/" local="130941733640000000" remote="130977792520000000" Dst="1" />
<file name="inlinetextarea.html" server="gpo.firespike.com/gpo.firespike.com/" local="130941733640000000" remote="130977792520000000" Dst="1" />
<file name="jquery.html" server="gpo.firespike.com/gpo.firespike.com/" local="130941733640000000" remote="130977792520000000" Dst="1" />
<file name="readonly.html" server="gpo.firespike.com/gpo.firespike.com/" local="130941733640000000" remote="130977792540000000" Dst="1" />
<file name="replacebyclass.html" server="gpo.firespike.com/gpo.firespike.com/" local="130941733640000000" remote="130977792540000000" Dst="1" />
<file name="replacebycode.html" server="gpo.firespike.com/gpo.firespike.com/" local="130941733640000000" remote="130977792550000000" Dst="1" />
<file name="sample.css" server="gpo.firespike.com/gpo.firespike.com/" local="130941733640000000" remote="130977792550000000" Dst="1" />
<file name="sample.js" server="gpo.firespike.com/gpo.firespike.com/" local="130941733640000000" remote="130977792550000000" Dst="1" />
<file name="sample_posteddata.php" server="gpo.firespike.com/gpo.firespike.com/" local="130941733640000000" remote="130977792550000000" Dst="1" />
<file name="tabindex.html" server="gpo.firespike.com/gpo.firespike.com/" local="130941733640000000" remote="130977792560000000" Dst="1" />
<file name="uicolor.html" server="gpo.firespike.com/gpo.firespike.com/" local="130941733640000000" remote="130977792570000000" Dst="1" />
<file name="uilanguages.html" server="gpo.firespike.com/gpo.firespike.com/" local="130941733640000000" remote="130977792570000000" Dst="1" />
<file name="xhtmlstyle.html" server="gpo.firespike.com/gpo.firespike.com/" local="130941733640000000" remote="130977792590000000" Dst="1" />
<file name="ajax.html" server="greener.firespike.com/greener.firespike.com/" local="130941733640000000" remote="130979465400000000" Dst="1" />
<file name="api.html" server="greener.firespike.com/greener.firespike.com/" local="130941733640000000" remote="130979465400000000" Dst="1" />
<file name="appendto.html" server="greener.firespike.com/greener.firespike.com/" local="130941733640000000" remote="130979465400000000" Dst="1" />
<file name="datafiltering.html" server="greener.firespike.com/greener.firespike.com/" local="130941733640000000" remote="130979465400000000" Dst="1" />
<file name="divreplace.html" server="greener.firespike.com/greener.firespike.com/" local="130941733640000000" remote="130979465400000000" Dst="1" />
<file name="inlineall.html" server="greener.firespike.com/greener.firespike.com/" local="130941733640000000" remote="130979465400000000" Dst="1" />
<file name="index.html" server="greener.firespike.com/greener.firespike.com/" local="130941733640000000" remote="130979465400000000" Dst="1" />
<file name="jquery.html" server="greener.firespike.com/greener.firespike.com/" local="130941733640000000" remote="130979465400000000" Dst="1" />
<file name="inlinebycode.html" server="greener.firespike.com/greener.firespike.com/" local="130941733640000000" remote="130979465400000000" Dst="1" />
<file name="inlinetextarea.html" server="greener.firespike.com/greener.firespike.com/" local="130941733640000000" remote="130979465400000000" Dst="1" />
<file name="replacebycode.html" server="greener.firespike.com/greener.firespike.com/" local="130941733640000000" remote="130979465400000000" Dst="1" />
<file name="readonly.html" server="greener.firespike.com/greener.firespike.com/" local="130941733640000000" remote="130979465400000000" Dst="1" />
<file name="replacebyclass.html" server="greener.firespike.com/greener.firespike.com/" local="130941733640000000" remote="130979465400000000" Dst="1" />
<file name="sample.css" server="greener.firespike.com/greener.firespike.com/" local="130941733640000000" remote="130979465400000000" Dst="1" />
<file name="sample.js" server="greener.firespike.com/greener.firespike.com/" local="130941733640000000" remote="130979465400000000" Dst="1" />
<file name="sample_posteddata.php" server="greener.firespike.com/greener.firespike.com/" local="130941733640000000" remote="130979465400000000" Dst="1" />
<file name="uicolor.html" server="greener.firespike.com/greener.firespike.com/" local="130941733640000000" remote="130979465400000000" Dst="1" />
<file name="tabindex.html" server="greener.firespike.com/greener.firespike.com/" local="130941733640000000" remote="130979465400000000" Dst="1" />
<file name="uilanguages.html" server="greener.firespike.com/greener.firespike.com/" local="130941733640000000" remote="130979465400000000" Dst="1" />
<file name="xhtmlstyle.html" server="greener.firespike.com/greener.firespike.com/" local="130941733640000000" remote="130979465400000000" Dst="1" />
<file name="ajax.html" server="192.185.136.177/public_html/" local="130941733640000000" remote="131021787000000000" Dst="1" />
<file name="api.html" server="192.185.136.177/public_html/" local="130941733640000000" remote="131021787000000000" Dst="1" />
<file name="appendto.html" server="192.185.136.177/public_html/" local="130941733640000000" remote="131021787000000000" Dst="1" />
<file name="datafiltering.html" server="192.185.136.177/public_html/" local="130941733640000000" remote="131021787000000000" Dst="1" />
<file name="divreplace.html" server="192.185.136.177/public_html/" local="130941733640000000" remote="131021787000000000" Dst="1" />
<file name="index.html" server="192.185.136.177/public_html/" local="130941733640000000" remote="131021787000000000" Dst="1" />
<file name="inlinetextarea.html" server="192.185.136.177/public_html/" local="130941733640000000" remote="131021787000000000" Dst="1" />
<file name="inlineall.html" server="192.185.136.177/public_html/" local="130941733640000000" remote="131021787000000000" Dst="1" />
<file name="inlinebycode.html" server="192.185.136.177/public_html/" local="130941733640000000" remote="131021787000000000" Dst="1" />
<file name="jquery.html" server="192.185.136.177/public_html/" local="130941733640000000" remote="131021787000000000" Dst="1" />
<file name="replacebycode.html" server="192.185.136.177/public_html/" local="130941733640000000" remote="131021787000000000" Dst="1" />
<file name="readonly.html" server="192.185.136.177/public_html/" local="130941733640000000" remote="131021787000000000" Dst="1" />
<file name="replacebyclass.html" server="192.185.136.177/public_html/" local="130941733640000000" remote="131021787000000000" Dst="1" />
<file name="sample.css" server="192.185.136.177/public_html/" local="130941733640000000" remote="131021787000000000" Dst="1" />
<file name="sample.js" server="192.185.136.177/public_html/" local="130941733640000000" remote="131021787000000000" Dst="1" />
<file name="sample_posteddata.php" server="192.185.136.177/public_html/" local="130941733640000000" remote="131021787000000000" Dst="1" />
<file name="tabindex.html" server="192.185.136.177/public_html/" local="130941733640000000" remote="131021787000000000" Dst="1" />
<file name="uicolor.html" server="192.185.136.177/public_html/" local="130941733640000000" remote="131021787000000000" Dst="1" />
<file name="uilanguages.html" server="192.185.136.177/public_html/" local="130941733640000000" remote="131021787000000000" Dst="1" />
<file name="xhtmlstyle.html" server="192.185.136.177/public_html/" local="130941733640000000" remote="131021787000000000" Dst="1" />
</dwsync>